MANIFEST.in
README.rst
REQUIREMENTS.txt
setup.py
StasFliKISS.egg-info/PKG-INFO
StasFliKISS.egg-info/SOURCES.txt
StasFliKISS.egg-info/dependency_links.txt
StasFliKISS.egg-info/entry_points.txt
StasFliKISS.egg-info/requires.txt
StasFliKISS.egg-info/top_level.txt
stasflikiss/__init__.py
stasflikiss/config.py
stasflikiss/forms.py
stasflikiss/launcher.py
stasflikiss/login.py
stasflikiss/models.py
stasflikiss/utils.py
stasflikiss/views.py
stasflikiss/static/css/base.css
stasflikiss/static/css/flikiss.css
stasflikiss/static/css/font-awesome.min.css
stasflikiss/static/css/layout.css
stasflikiss/static/css/pygments.css
stasflikiss/static/css/skeleton.css
stasflikiss/static/fonts/FontAwesome.otf
stasflikiss/static/fonts/fontawesome-webfont.eot
stasflikiss/static/fonts/fontawesome-webfont.svg
stasflikiss/static/fonts/fontawesome-webfont.ttf
stasflikiss/static/fonts/fontawesome-webfont.woff
stasflikiss/static/img/favicon.png
stasflikiss/static/img/logo.png
stasflikiss/static/js/editor.js
stasflikiss/templates/base.html
stasflikiss/templates/edit.html
stasflikiss/templates/login.html
stasflikiss/templates/page.html