Metadata-Version: 1.1
Name: StasFliKISS
Version: 0.1.2
Summary: Wiki engine based on Markdown flat files powered by Flask. Fork from StasEvseev.
Home-page: UNKNOWN
Author: Stas Evseev
Author-email: stasevseev@gmail.com
License: UNKNOWN
Platform: UNKNOWN
Classifier: Programming Language :: Python
Classifier: Development Status :: 4 - Beta
Classifier: Environment :: Web Environment
Classifier: Framework :: Flask
Classifier: Topic :: Internet :: WWW/HTTP :: WSGI :: Application
Classifier: License :: OSI Approved :: GNU General Public License v3 or later (GPLv3+)
Classifier: Natural Language :: English
Classifier: Programming Language :: Python :: 2.7
